ast_drawer_ses/ast_basic.py
ast_drawer_ses/ast_improved.py
ast_drawer_ses/fib.py
ast_drawer_ses/main.py
ast_drawer_ses-0.0.4.dist-info/METADATA
ast_drawer_ses-0.0.4.dist-info/WHEEL
ast_drawer_ses-0.0.4.dist-info/top_level.txt
ast_drawer_ses-0.0.4.dist-info/RECORD
